setuptools_scm_git_semver/__init__.py
setuptools_scm_git_semver-0.3.0.dist-info/LICENSE
setuptools_scm_git_semver-0.3.0.dist-info/METADATA
setuptools_scm_git_semver-0.3.0.dist-info/WHEEL
setuptools_scm_git_semver-0.3.0.dist-info/entry_points.txt
setuptools_scm_git_semver-0.3.0.dist-info/top_level.txt
setuptools_scm_git_semver-0.3.0.dist-info/zip-safe
setuptools_scm_git_semver-0.3.0.dist-info/RECORD
