Metadata-Version: 2.1
Name: setuptools-scm-git-semver
Version: 0.3.0
Summary: SemVer-compatible plugin for setuptools_scm.
Home-page: https://github.com/cloudreach/setuptools_scm_git_semver
Author: Cloudreach Software Team Ops Management
Author-email: sw-team-ops-management@cloudreach.com
License: MIT
Platform: UNKNOWN
Requires-Python: >=3.6
License-File: LICENSE
Requires-Dist: setuptools-scm (>=6.3.1)
